pylinkam/__init__.py
pylinkam/interface.py
pylinkam/sdk.py
pylinkam/util.py
pylinkam-1.2.6.dist-info/LICENSE.txt
pylinkam-1.2.6.dist-info/METADATA
pylinkam-1.2.6.dist-info/WHEEL
pylinkam-1.2.6.dist-info/top_level.txt
pylinkam-1.2.6.dist-info/RECORD
